hoe/__init__.py
hoe/main.py
hoe-0.0.1.dist-info/LICENSE.md
hoe-0.0.1.dist-info/METADATA
hoe-0.0.1.dist-info/WHEEL
hoe-0.0.1.dist-info/entry_points.txt
hoe-0.0.1.dist-info/top_level.txt
hoe-0.0.1.dist-info/RECORD
